seleqt/__init__.py
seleqt/selection.py
seleqt/stats.py
seleqt-1.0.dist-info/LICENSE
seleqt-1.0.dist-info/METADATA
seleqt-1.0.dist-info/WHEEL
seleqt-1.0.dist-info/top_level.txt
seleqt-1.0.dist-info/RECORD
