Metadata-Version: 2.1
Name: seleqt
Version: 1.0
Summary: Quantum Feature Seletion (QFS) algorithm
Author-email: Sascha Mücke <sascha.muecke@tu-dortmund.de>
Classifier: Programming Language :: Python :: 3
Classifier: License :: OSI Approved :: MIT License
Classifier: Operating System :: OS Independent
Requires-Python: >=3.8
License-File: LICENSE
Requires-Dist: numpy (>=1.23.5)
